snmpclient
