Metadata-Version: 1.1
Name: python-snmpclient
Version: 0.5
Summary: Wrapper around pysnmp4 for easier snmp querying
Home-page: http://github.com/seveas/python-snmpclient
Author: Dennis Kaarsemaker
Author-email: dennis@kaarsemaker.net
License: UNKNOWN
Platform: UNKNOWN
Classifier: Intended Audience :: Developers
Classifier: Intended Audience :: System Administrators
Classifier: Operating System :: OS Independent
Classifier: Topic :: System :: Monitoring
Classifier: Topic :: Software Development
